software_company/__init__.py
software_company/agent_adapter.py
software_company/cli/__init__.py
software_company/cli/aider.py
software_company/cli/amazonq.py
software_company/cli/base.py
software_company/cli/gemini.py
software_company/cli/github_copilot.py
software_company/cli/opencode.py
software_company/cli/utils.py
software_company/config.py
software_company/default_config.json
software_company/main.py
software_company/reporting.py
software_company/rich_help.py
software_company/sandbox.py
software_company/state_manager.py
software_company/templates/development.json
software_company/templates/feature_recommendation.json
software_company/templates/full_waterfall.json
software_company/templates/planning.json
software_company/templates/testing.json
software_company/tui/__init__.py
software_company/tui/adapter.py
software_company/tui/app.py
software_company/tui/screens.py
software_company/tui/widgets.py
software_company/ui.py
software_company/utils.py
software_company/workflow.py
autogen_software_company-0.12.4.dist-info/METADATA
autogen_software_company-0.12.4.dist-info/WHEEL
autogen_software_company-0.12.4.dist-info/entry_points.txt
autogen_software_company-0.12.4.dist-info/RECORD
