Metadata-Version: 2.4
Name: autogen-software-company
Version: 0.12.4
Summary: A CLI-based AutoGen agent team simulating a software company.
Author: amirmuha
Author-email: mirzaii4046@gmail.com
Requires-Python: >=3.11,<4.0
Classifier: Programming Language :: Python :: 3
Classifier: Programming Language :: Python :: 3.11
Classifier: Programming Language :: Python :: 3.12
Classifier: Programming Language :: Python :: 3.13
Classifier: Programming Language :: Python :: 3.14
Requires-Dist: autogen-agentchat (>=0.7.5,<0.8.0)
Requires-Dist: autogen-core (>=0.7.5,<0.8.0)
Requires-Dist: autogen-ext[azure,openai] (>=0.7.5,<0.8.0)
Requires-Dist: openai (>=2.11.0,<3.0.0)
Requires-Dist: pexpect (>=4.9.0,<5.0.0)
Requires-Dist: python-dotenv (>=0.9.9)
Requires-Dist: requests (>=2.32.5,<3.0.0)
Requires-Dist: rich (>=14.2.0,<15.0.0)
Requires-Dist: textual (>=0.70.0)
